apiwrapper/__init__.py
apiwrapper/apiwrapper.py
apiwrapper-0.1.8.dist-info/DESCRIPTION.rst
apiwrapper-0.1.8.dist-info/METADATA
apiwrapper-0.1.8.dist-info/metadata.json
apiwrapper-0.1.8.dist-info/RECORD
apiwrapper-0.1.8.dist-info/top_level.txt
apiwrapper-0.1.8.dist-info/WHEEL
