Metadata-Version: 1.1
Name: apiwrapper
Version: 0.1.8
Summary: Simple API Wrapper
Home-page: https://github.com/ardydedase/apiwrapper
Author: Ardy Dedase
Author-email: ardy.dedase@gmail.com
License: BSD
Keywords: apiwrapper
Platform: UNKNOWN
Classifier: Development Status :: 2 - Pre-Alpha
Classifier: Intended Audience :: Developers
Classifier: License :: OSI Approved :: BSD License
Classifier: Natural Language :: English
Classifier: Programming Language :: Python :: 2
Classifier: Programming Language :: Python :: 2.6
Classifier: Programming Language :: Python :: 2.7
Classifier: Programming Language :: Python :: 3
Classifier: Programming Language :: Python :: 3.3
Classifier: Programming Language :: Python :: 3.4
